{
  "type": "File",
  "start": 0,
  "end": 271,
  "loc": {
    "start": {
      "line": 1,
      "column": 0
    },
    "end": {
      "line": 17,
      "column": 0
    }
  },
  "program": {
    "type": "Program",
    "start": 0,
    "end": 271,
    "loc": {
      "start": {
        "line": 1,
        "column": 0
      },
      "end": {
        "line": 17,
        "column": 0
      }
    },
    "sourceType": "module",
    "body": [
      {
        "type": "VariableDeclaration",
        "start": 36,
        "end": 60,
        "loc": {
          "start": {
            "line": 4,
            "column": 0
          },
          "end": {
            "line": 4,
            "column": 24
          }
        },
        "declarations": [
          {
            "type": "VariableDeclarator",
            "start": 42,
            "end": 59,
            "loc": {
              "start": {
                "line": 4,
                "column": 6
              },
              "end": {
                "line": 4,
                "column": 23
              }
            },
            "id": {
              "type": "Identifier",
              "start": 42,
              "end": 54,
              "loc": {
                "start": {
                  "line": 4,
                  "column": 6
                },
                "end": {
                  "line": 4,
                  "column": 18
                },
                "identifierName": "initialState"
              },
              "name": "initialState",
              "leadingComments": null
            },
            "init": {
              "type": "ObjectExpression",
              "start": 57,
              "end": 59,
              "loc": {
                "start": {
                  "line": 4,
                  "column": 21
                },
                "end": {
                  "line": 4,
                  "column": 23
                }
              },
              "properties": []
            },
            "leadingComments": null
          }
        ],
        "kind": "const",
        "leadingComments": [
          {
            "type": "CommentLine",
            "value": " Import Actions",
            "start": 0,
            "end": 17,
            "loc": {
              "start": {
                "line": 1,
                "column": 0
              },
              "end": {
                "line": 1,
                "column": 17
              }
            }
          },
          {
            "type": "CommentLine",
            "value": " Initial State",
            "start": 19,
            "end": 35,
            "loc": {
              "start": {
                "line": 3,
                "column": 0
              },
              "end": {
                "line": 3,
                "column": 16
              }
            }
          }
        ]
      },
      {
        "type": "Identifier",
        "start": 62,
        "end": 201,
        "loc": {
          "start": {
            "line": 6,
            "column": 0
          },
          "end": {
            "line": 11,
            "column": 2
          }
        },
        "declarations": [
          {
            "type": "VariableDeclarator",
            "start": 68,
            "end": 200,
            "loc": {
              "start": {
                "line": 6,
                "column": 6
              },
              "end": {
                "line": 11,
                "column": 1
              }
            },
            "id": {
              "type": "Identifier",
              "start": 68,
              "end": 84,
              "loc": {
                "start": {
                  "line": 6,
                  "column": 6
                },
                "end": {
                  "line": 6,
                  "column": 22
                },
                "identifierName": "ContainerReducer"
              },
              "name": "ContainerReducer"
            },
            "init": {
              "type": "ArrowFunctionExpression",
              "start": 87,
              "end": 200,
              "loc": {
                "start": {
                  "line": 6,
                  "column": 25
                },
                "end": {
                  "line": 11,
                  "column": 1
                }
              },
              "id": null,
              "generator": false,
              "expression": false,
              "async": false,
              "params": [
                {
                  "type": "AssignmentPattern",
                  "start": 88,
                  "end": 108,
                  "loc": {
                    "start": {
                      "line": 6,
                      "column": 26
                    },
                    "end": {
                      "line": 6,
                      "column": 46
                    }
                  },
                  "left": {
                    "type": "Identifier",
                    "start": 88,
                    "end": 93,
                    "loc": {
                      "start": {
                        "line": 6,
                        "column": 26
                      },
                      "end": {
                        "line": 6,
                        "column": 31
                      },
                      "identifierName": "state"
                    },
                    "name": "state"
                  },
                  "right": {
                    "type": "Identifier",
                    "start": 96,
                    "end": 108,
                    "loc": {
                      "start": {
                        "line": 6,
                        "column": 34
                      },
                      "end": {
                        "line": 6,
                        "column": 46
                      },
                      "identifierName": "initialState"
                    },
                    "name": "initialState"
                  }
                },
                {
                  "type": "Identifier",
                  "start": 110,
                  "end": 116,
                  "loc": {
                    "start": {
                      "line": 6,
                      "column": 48
                    },
                    "end": {
                      "line": 6,
                      "column": 54
                    },
                    "identifierName": "action"
                  },
                  "name": "action"
                }
              ],
              "body": {
                "type": "BlockStatement",
                "start": 121,
                "end": 200,
                "loc": {
                  "start": {
                    "line": 6,
                    "column": 59
                  },
                  "end": {
                    "line": 11,
                    "column": 1
                  }
                },
                "body": [
                  {
                    "type": "SwitchStatement",
                    "start": 127,
                    "end": 198,
                    "loc": {
                      "start": {
                        "line": 7,
                        "column": 4
                      },
                      "end": {
                        "line": 10,
                        "column": 5
                      }
                    },
                    "discriminant": {
                      "type": "MemberExpression",
                      "start": 135,
                      "end": 146,
                      "loc": {
                        "start": {
                          "line": 7,
                          "column": 12
                        },
                        "end": {
                          "line": 7,
                          "column": 23
                        }
                      },
                      "object": {
                        "type": "Identifier",
                        "start": 135,
                        "end": 141,
                        "loc": {
                          "start": {
                            "line": 7,
                            "column": 12
                          },
                          "end": {
                            "line": 7,
                            "column": 18
                          },
                          "identifierName": "action"
                        },
                        "name": "action"
                      },
                      "property": {
                        "type": "Identifier",
                        "start": 142,
                        "end": 146,
                        "loc": {
                          "start": {
                            "line": 7,
                            "column": 19
                          },
                          "end": {
                            "line": 7,
                            "column": 23
                          },
                          "identifierName": "type"
                        },
                        "name": "type"
                      },
                      "computed": false
                    },
                    "cases": [
                      {
                        "type": "SwitchCase",
                        "start": 158,
                        "end": 192,
                        "loc": {
                          "start": {
                            "line": 8,
                            "column": 8
                          },
                          "end": {
                            "line": 9,
                            "column": 25
                          }
                        },
                        "consequent": [
                          {
                            "type": "ReturnStatement",
                            "start": 179,
                            "end": 192,
                            "loc": {
                              "start": {
                                "line": 9,
                                "column": 12
                              },
                              "end": {
                                "line": 9,
                                "column": 25
                              }
                            },
                            "argument": {
                              "type": "Identifier",
                              "start": 186,
                              "end": 191,
                              "loc": {
                                "start": {
                                  "line": 9,
                                  "column": 19
                                },
                                "end": {
                                  "line": 9,
                                  "column": 24
                                },
                                "identifierName": "state"
                              },
                              "name": "state"
                            }
                          }
                        ],
                        "test": null
                      }
                    ]
                  }
                ],
                "directives": []
              }
            }
          }
        ],
        "kind": "const",
        "trailingComments": [],
        "name": "_",
        "leadingComments": []
      },
      {
        "type": "Identifier",
        "start": 238,
        "end": 270,
        "loc": {
          "start": {
            "line": 16,
            "column": 0
          },
          "end": {
            "line": 16,
            "column": 32
          }
        },
        "declaration": {
          "type": "Identifier",
          "start": 253,
          "end": 269,
          "loc": {
            "start": {
              "line": 16,
              "column": 15
            },
            "end": {
              "line": 16,
              "column": 31
            },
            "identifierName": "ContainerReducer"
          },
          "name": "ContainerReducer",
          "leadingComments": null
        },
        "leadingComments": [],
        "name": "_",
        "trailingComments": []
      },
      {
        "type": "ExportDefaultDeclaration",
        "start": 238,
        "end": 270,
        "loc": {
          "start": {
            "line": 16,
            "column": 0
          },
          "end": {
            "line": 16,
            "column": 32
          }
        },
        "declaration": {
          "type": "VariableDeclaration",
          "start": 62,
          "end": 201,
          "loc": {
            "start": {
              "line": 6,
              "column": 0
            },
            "end": {
              "line": 11,
              "column": 2
            }
          },
          "declarations": [
            {
              "type": "VariableDeclarator",
              "start": 68,
              "end": 200,
              "loc": {
                "start": {
                  "line": 6,
                  "column": 6
                },
                "end": {
                  "line": 11,
                  "column": 1
                }
              },
              "id": {
                "type": "Identifier",
                "start": 68,
                "end": 84,
                "loc": {
                  "start": {
                    "line": 6,
                    "column": 6
                  },
                  "end": {
                    "line": 6,
                    "column": 22
                  },
                  "identifierName": "ContainerReducer"
                },
                "name": "ContainerReducer"
              },
              "init": {
                "type": "ArrowFunctionExpression",
                "start": 87,
                "end": 200,
                "loc": {
                  "start": {
                    "line": 6,
                    "column": 25
                  },
                  "end": {
                    "line": 11,
                    "column": 1
                  }
                },
                "id": {
                  "type": "Identifier",
                  "start": 68,
                  "end": 84,
                  "loc": {
                    "start": {
                      "line": 6,
                      "column": 6
                    },
                    "end": {
                      "line": 6,
                      "column": 22
                    },
                    "identifierName": "ContainerReducer"
                  },
                  "name": "ContainerReducer"
                },
                "generator": false,
                "expression": false,
                "async": false,
                "params": [
                  {
                    "type": "AssignmentPattern",
                    "start": 88,
                    "end": 108,
                    "loc": {
                      "start": {
                        "line": 6,
                        "column": 26
                      },
                      "end": {
                        "line": 6,
                        "column": 46
                      }
                    },
                    "left": {
                      "type": "Identifier",
                      "start": 88,
                      "end": 93,
                      "loc": {
                        "start": {
                          "line": 6,
                          "column": 26
                        },
                        "end": {
                          "line": 6,
                          "column": 31
                        },
                        "identifierName": "state"
                      },
                      "name": "state"
                    },
                    "right": {
                      "type": "Identifier",
                      "start": 96,
                      "end": 108,
                      "loc": {
                        "start": {
                          "line": 6,
                          "column": 34
                        },
                        "end": {
                          "line": 6,
                          "column": 46
                        },
                        "identifierName": "initialState"
                      },
                      "name": "initialState"
                    }
                  },
                  {
                    "type": "Identifier",
                    "start": 110,
                    "end": 116,
                    "loc": {
                      "start": {
                        "line": 6,
                        "column": 48
                      },
                      "end": {
                        "line": 6,
                        "column": 54
                      },
                      "identifierName": "action"
                    },
                    "name": "action"
                  }
                ],
                "body": {
                  "type": "BlockStatement",
                  "start": 121,
                  "end": 200,
                  "loc": {
                    "start": {
                      "line": 6,
                      "column": 59
                    },
                    "end": {
                      "line": 11,
                      "column": 1
                    }
                  },
                  "body": [
                    {
                      "type": "SwitchStatement",
                      "start": 127,
                      "end": 198,
                      "loc": {
                        "start": {
                          "line": 7,
                          "column": 4
                        },
                        "end": {
                          "line": 10,
                          "column": 5
                        }
                      },
                      "discriminant": {
                        "type": "MemberExpression",
                        "start": 135,
                        "end": 146,
                        "loc": {
                          "start": {
                            "line": 7,
                            "column": 12
                          },
                          "end": {
                            "line": 7,
                            "column": 23
                          }
                        },
                        "object": {
                          "type": "Identifier",
                          "start": 135,
                          "end": 141,
                          "loc": {
                            "start": {
                              "line": 7,
                              "column": 12
                            },
                            "end": {
                              "line": 7,
                              "column": 18
                            },
                            "identifierName": "action"
                          },
                          "name": "action"
                        },
                        "property": {
                          "type": "Identifier",
                          "start": 142,
                          "end": 146,
                          "loc": {
                            "start": {
                              "line": 7,
                              "column": 19
                            },
                            "end": {
                              "line": 7,
                              "column": 23
                            },
                            "identifierName": "type"
                          },
                          "name": "type"
                        },
                        "computed": false
                      },
                      "cases": [
                        {
                          "type": "SwitchCase",
                          "start": 158,
                          "end": 192,
                          "loc": {
                            "start": {
                              "line": 8,
                              "column": 8
                            },
                            "end": {
                              "line": 9,
                              "column": 25
                            }
                          },
                          "consequent": [
                            {
                              "type": "ReturnStatement",
                              "start": 179,
                              "end": 192,
                              "loc": {
                                "start": {
                                  "line": 9,
                                  "column": 12
                                },
                                "end": {
                                  "line": 9,
                                  "column": 25
                                }
                              },
                              "argument": {
                                "type": "Identifier",
                                "start": 186,
                                "end": 191,
                                "loc": {
                                  "start": {
                                    "line": 9,
                                    "column": 19
                                  },
                                  "end": {
                                    "line": 9,
                                    "column": 24
                                  },
                                  "identifierName": "state"
                                },
                                "name": "state"
                              }
                            }
                          ],
                          "test": null
                        }
                      ]
                    }
                  ],
                  "directives": []
                }
              }
            }
          ],
          "kind": "const",
          "trailingComments": [
            {
              "type": "CommentBlock",
              "value": " Selectors ",
              "start": 203,
              "end": 218,
              "loc": {
                "start": {
                  "line": 13,
                  "column": 0
                },
                "end": {
                  "line": 13,
                  "column": 15
                }
              }
            },
            {
              "type": "CommentLine",
              "value": " Export Reducer",
              "start": 220,
              "end": 237,
              "loc": {
                "start": {
                  "line": 15,
                  "column": 0
                },
                "end": {
                  "line": 15,
                  "column": 17
                }
              }
            }
          ],
          "leadingComments": [
            {
              "type": "CommentBlock",
              "value": " Selectors ",
              "start": 203,
              "end": 218,
              "loc": {
                "start": {
                  "line": 13,
                  "column": 0
                },
                "end": {
                  "line": 13,
                  "column": 15
                }
              }
            },
            {
              "type": "CommentLine",
              "value": " Export Reducer",
              "start": 220,
              "end": 237,
              "loc": {
                "start": {
                  "line": 15,
                  "column": 0
                },
                "end": {
                  "line": 15,
                  "column": 17
                }
              }
            }
          ]
        },
        "leadingComments": [
          {
            "type": "CommentBlock",
            "value": " Selectors ",
            "start": 203,
            "end": 218,
            "loc": {
              "start": {
                "line": 13,
                "column": 0
              },
              "end": {
                "line": 13,
                "column": 15
              }
            }
          },
          {
            "type": "CommentLine",
            "value": " Export Reducer",
            "start": 220,
            "end": 237,
            "loc": {
              "start": {
                "line": 15,
                "column": 0
              },
              "end": {
                "line": 15,
                "column": 17
              }
            }
          }
        ]
      }
    ],
    "directives": []
  },
  "comments": [
    {
      "type": "CommentLine",
      "value": " Import Actions",
      "start": 0,
      "end": 17,
      "loc": {
        "start": {
          "line": 1,
          "column": 0
        },
        "end": {
          "line": 1,
          "column": 17
        }
      }
    },
    {
      "type": "CommentLine",
      "value": " Initial State",
      "start": 19,
      "end": 35,
      "loc": {
        "start": {
          "line": 3,
          "column": 0
        },
        "end": {
          "line": 3,
          "column": 16
        }
      }
    },
    {
      "type": "CommentBlock",
      "value": " Selectors ",
      "start": 203,
      "end": 218,
      "loc": {
        "start": {
          "line": 13,
          "column": 0
        },
        "end": {
          "line": 13,
          "column": 15
        }
      }
    },
    {
      "type": "CommentLine",
      "value": " Export Reducer",
      "start": 220,
      "end": 237,
      "loc": {
        "start": {
          "line": 15,
          "column": 0
        },
        "end": {
          "line": 15,
          "column": 17
        }
      }
    }
  ],
  "tokens": [
    {
      "type": "CommentLine",
      "value": " Import Actions",
      "start": 0,
      "end": 17,
      "loc": {
        "start": {
          "line": 1,
          "column": 0
        },
        "end": {
          "line": 1,
          "column": 17
        }
      }
    },
    {
      "type": "CommentLine",
      "value": " Initial State",
      "start": 19,
      "end": 35,
      "loc": {
        "start": {
          "line": 3,
          "column": 0
        },
        "end": {
          "line": 3,
          "column": 16
        }
      }
    },
    {
      "type": {
        "label": "const",
        "keyword": "const",
        "beforeExpr": false,
        "startsExpr": false,
        "rightAssociative": false,
        "isLoop": false,
        "isAssign": false,
        "prefix": false,
        "postfix": false,
        "binop": null,
        "updateContext": null
      },
      "value": "const",
      "start": 36,
      "end": 41,
      "loc": {
        "start": {
          "line": 4,
          "column": 0
        },
        "end": {
          "line": 4,
          "column": 5
        }
      }
    },
    {
      "type": {
        "label": "name",
        "beforeExpr": false,
        "startsExpr": true,
        "rightAssociative": false,
        "isLoop": false,
        "isAssign": false,
        "prefix": false,
        "postfix": false,
        "binop": null
      },
      "value": "initialState",
      "start": 42,
      "end": 54,
      "loc": {
        "start": {
          "line": 4,
          "column": 6
        },
        "end": {
          "line": 4,
          "column": 18
        }
      }
    },
    {
      "type": {
        "label": "=",
        "beforeExpr": true,
        "startsExpr": false,
        "rightAssociative": false,
        "isLoop": false,
        "isAssign": true,
        "prefix": false,
        "postfix": false,
        "binop": null,
        "updateContext": null
      },
      "value": "=",
      "start": 55,
      "end": 56,
      "loc": {
        "start": {
          "line": 4,
          "column": 19
        },
        "end": {
          "line": 4,
          "column": 20
        }
      }
    },
    {
      "type": {
        "label": "{",
        "beforeExpr": true,
        "startsExpr": true,
        "rightAssociative": false,
        "isLoop": false,
        "isAssign": false,
        "prefix": false,
        "postfix": false,
        "binop": null
      },
      "start": 57,
      "end": 58,
      "loc": {
        "start": {
          "line": 4,
          "column": 21
        },
        "end": {
          "line": 4,
          "column": 22
        }
      }
    },
    {
      "type": {
        "label": "}",
        "beforeExpr": false,
        "startsExpr": false,
        "rightAssociative": false,
        "isLoop": false,
        "isAssign": false,
        "prefix": false,
        "postfix": false,
        "binop": null
      },
      "start": 58,
      "end": 59,
      "loc": {
        "start": {
          "line": 4,
          "column": 22
        },
        "end": {
          "line": 4,
          "column": 23
        }
      }
    },
    {
      "type": {
        "label": ";",
        "beforeExpr": true,
        "startsExpr": false,
        "rightAssociative": false,
        "isLoop": false,
        "isAssign": false,
        "prefix": false,
        "postfix": false,
        "binop": null,
        "updateContext": null
      },
      "start": 59,
      "end": 60,
      "loc": {
        "start": {
          "line": 4,
          "column": 23
        },
        "end": {
          "line": 4,
          "column": 24
        }
      }
    },
    {
      "type": {
        "label": "const",
        "keyword": "const",
        "beforeExpr": false,
        "startsExpr": false,
        "rightAssociative": false,
        "isLoop": false,
        "isAssign": false,
        "prefix": false,
        "postfix": false,
        "binop": null,
        "updateContext": null
      },
      "value": "const",
      "start": 62,
      "end": 67,
      "loc": {
        "start": {
          "line": 6,
          "column": 0
        },
        "end": {
          "line": 6,
          "column": 5
        }
      }
    },
    {
      "type": {
        "label": "name",
        "beforeExpr": false,
        "startsExpr": true,
        "rightAssociative": false,
        "isLoop": false,
        "isAssign": false,
        "prefix": false,
        "postfix": false,
        "binop": null
      },
      "value": "ContainerReducer",
      "start": 68,
      "end": 84,
      "loc": {
        "start": {
          "line": 6,
          "column": 6
        },
        "end": {
          "line": 6,
          "column": 22
        }
      }
    },
    {
      "type": {
        "label": "=",
        "beforeExpr": true,
        "startsExpr": false,
        "rightAssociative": false,
        "isLoop": false,
        "isAssign": true,
        "prefix": false,
        "postfix": false,
        "binop": null,
        "updateContext": null
      },
      "value": "=",
      "start": 85,
      "end": 86,
      "loc": {
        "start": {
          "line": 6,
          "column": 23
        },
        "end": {
          "line": 6,
          "column": 24
        }
      }
    },
    {
      "type": {
        "label": "(",
        "beforeExpr": true,
        "startsExpr": true,
        "rightAssociative": false,
        "isLoop": false,
        "isAssign": false,
        "prefix": false,
        "postfix": false,
        "binop": null
      },
      "start": 87,
      "end": 88,
      "loc": {
        "start": {
          "line": 6,
          "column": 25
        },
        "end": {
          "line": 6,
          "column": 26
        }
      }
    },
    {
      "type": {
        "label": "name",
        "beforeExpr": false,
        "startsExpr": true,
        "rightAssociative": false,
        "isLoop": false,
        "isAssign": false,
        "prefix": false,
        "postfix": false,
        "binop": null
      },
      "value": "state",
      "start": 88,
      "end": 93,
      "loc": {
        "start": {
          "line": 6,
          "column": 26
        },
        "end": {
          "line": 6,
          "column": 31
        }
      }
    },
    {
      "type": {
        "label": "=",
        "beforeExpr": true,
        "startsExpr": false,
        "rightAssociative": false,
        "isLoop": false,
        "isAssign": true,
        "prefix": false,
        "postfix": false,
        "binop": null,
        "updateContext": null
      },
      "value": "=",
      "start": 94,
      "end": 95,
      "loc": {
        "start": {
          "line": 6,
          "column": 32
        },
        "end": {
          "line": 6,
          "column": 33
        }
      }
    },
    {
      "type": {
        "label": "name",
        "beforeExpr": false,
        "startsExpr": true,
        "rightAssociative": false,
        "isLoop": false,
        "isAssign": false,
        "prefix": false,
        "postfix": false,
        "binop": null
      },
      "value": "initialState",
      "start": 96,
      "end": 108,
      "loc": {
        "start": {
          "line": 6,
          "column": 34
        },
        "end": {
          "line": 6,
          "column": 46
        }
      }
    },
    {
      "type": {
        "label": ",",
        "beforeExpr": true,
        "startsExpr": false,
        "rightAssociative": false,
        "isLoop": false,
        "isAssign": false,
        "prefix": false,
        "postfix": false,
        "binop": null,
        "updateContext": null
      },
      "start": 108,
      "end": 109,
      "loc": {
        "start": {
          "line": 6,
          "column": 46
        },
        "end": {
          "line": 6,
          "column": 47
        }
      }
    },
    {
      "type": {
        "label": "name",
        "beforeExpr": false,
        "startsExpr": true,
        "rightAssociative": false,
        "isLoop": false,
        "isAssign": false,
        "prefix": false,
        "postfix": false,
        "binop": null
      },
      "value": "action",
      "start": 110,
      "end": 116,
      "loc": {
        "start": {
          "line": 6,
          "column": 48
        },
        "end": {
          "line": 6,
          "column": 54
        }
      }
    },
    {
      "type": {
        "label": ")",
        "beforeExpr": false,
        "startsExpr": false,
        "rightAssociative": false,
        "isLoop": false,
        "isAssign": false,
        "prefix": false,
        "postfix": false,
        "binop": null
      },
      "start": 116,
      "end": 117,
      "loc": {
        "start": {
          "line": 6,
          "column": 54
        },
        "end": {
          "line": 6,
          "column": 55
        }
      }
    },
    {
      "type": {
        "label": "=>",
        "beforeExpr": true,
        "startsExpr": false,
        "rightAssociative": false,
        "isLoop": false,
        "isAssign": false,
        "prefix": false,
        "postfix": false,
        "binop": null,
        "updateContext": null
      },
      "start": 118,
      "end": 120,
      "loc": {
        "start": {
          "line": 6,
          "column": 56
        },
        "end": {
          "line": 6,
          "column": 58
        }
      }
    },
    {
      "type": {
        "label": "{",
        "beforeExpr": true,
        "startsExpr": true,
        "rightAssociative": false,
        "isLoop": false,
        "isAssign": false,
        "prefix": false,
        "postfix": false,
        "binop": null
      },
      "start": 121,
      "end": 122,
      "loc": {
        "start": {
          "line": 6,
          "column": 59
        },
        "end": {
          "line": 6,
          "column": 60
        }
      }
    },
    {
      "type": {
        "label": "switch",
        "keyword": "switch",
        "beforeExpr": false,
        "startsExpr": false,
        "rightAssociative": false,
        "isLoop": false,
        "isAssign": false,
        "prefix": false,
        "postfix": false,
        "binop": null,
        "updateContext": null
      },
      "value": "switch",
      "start": 127,
      "end": 133,
      "loc": {
        "start": {
          "line": 7,
          "column": 4
        },
        "end": {
          "line": 7,
          "column": 10
        }
      }
    },
    {
      "type": {
        "label": "(",
        "beforeExpr": true,
        "startsExpr": true,
        "rightAssociative": false,
        "isLoop": false,
        "isAssign": false,
        "prefix": false,
        "postfix": false,
        "binop": null
      },
      "start": 134,
      "end": 135,
      "loc": {
        "start": {
          "line": 7,
          "column": 11
        },
        "end": {
          "line": 7,
          "column": 12
        }
      }
    },
    {
      "type": {
        "label": "name",
        "beforeExpr": false,
        "startsExpr": true,
        "rightAssociative": false,
        "isLoop": false,
        "isAssign": false,
        "prefix": false,
        "postfix": false,
        "binop": null
      },
      "value": "action",
      "start": 135,
      "end": 141,
      "loc": {
        "start": {
          "line": 7,
          "column": 12
        },
        "end": {
          "line": 7,
          "column": 18
        }
      }
    },
    {
      "type": {
        "label": ".",
        "beforeExpr": false,
        "startsExpr": false,
        "rightAssociative": false,
        "isLoop": false,
        "isAssign": false,
        "prefix": false,
        "postfix": false,
        "binop": null,
        "updateContext": null
      },
      "start": 141,
      "end": 142,
      "loc": {
        "start": {
          "line": 7,
          "column": 18
        },
        "end": {
          "line": 7,
          "column": 19
        }
      }
    },
    {
      "type": {
        "label": "name",
        "beforeExpr": false,
        "startsExpr": true,
        "rightAssociative": false,
        "isLoop": false,
        "isAssign": false,
        "prefix": false,
        "postfix": false,
        "binop": null
      },
      "value": "type",
      "start": 142,
      "end": 146,
      "loc": {
        "start": {
          "line": 7,
          "column": 19
        },
        "end": {
          "line": 7,
          "column": 23
        }
      }
    },
    {
      "type": {
        "label": ")",
        "beforeExpr": false,
        "startsExpr": false,
        "rightAssociative": false,
        "isLoop": false,
        "isAssign": false,
        "prefix": false,
        "postfix": false,
        "binop": null
      },
      "start": 146,
      "end": 147,
      "loc": {
        "start": {
          "line": 7,
          "column": 23
        },
        "end": {
          "line": 7,
          "column": 24
        }
      }
    },
    {
      "type": {
        "label": "{",
        "beforeExpr": true,
        "startsExpr": true,
        "rightAssociative": false,
        "isLoop": false,
        "isAssign": false,
        "prefix": false,
        "postfix": false,
        "binop": null
      },
      "start": 148,
      "end": 149,
      "loc": {
        "start": {
          "line": 7,
          "column": 25
        },
        "end": {
          "line": 7,
          "column": 26
        }
      }
    },
    {
      "type": {
        "label": "default",
        "keyword": "default",
        "beforeExpr": true,
        "startsExpr": false,
        "rightAssociative": false,
        "isLoop": false,
        "isAssign": false,
        "prefix": false,
        "postfix": false,
        "binop": null,
        "updateContext": null
      },
      "value": "default",
      "start": 158,
      "end": 165,
      "loc": {
        "start": {
          "line": 8,
          "column": 8
        },
        "end": {
          "line": 8,
          "column": 15
        }
      }
    },
    {
      "type": {
        "label": ":",
        "beforeExpr": true,
        "startsExpr": false,
        "rightAssociative": false,
        "isLoop": false,
        "isAssign": false,
        "prefix": false,
        "postfix": false,
        "binop": null,
        "updateContext": null
      },
      "start": 165,
      "end": 166,
      "loc": {
        "start": {
          "line": 8,
          "column": 15
        },
        "end": {
          "line": 8,
          "column": 16
        }
      }
    },
    {
      "type": {
        "label": "return",
        "keyword": "return",
        "beforeExpr": true,
        "startsExpr": false,
        "rightAssociative": false,
        "isLoop": false,
        "isAssign": false,
        "prefix": false,
        "postfix": false,
        "binop": null,
        "updateContext": null
      },
      "value": "return",
      "start": 179,
      "end": 185,
      "loc": {
        "start": {
          "line": 9,
          "column": 12
        },
        "end": {
          "line": 9,
          "column": 18
        }
      }
    },
    {
      "type": {
        "label": "name",
        "beforeExpr": false,
        "startsExpr": true,
        "rightAssociative": false,
        "isLoop": false,
        "isAssign": false,
        "prefix": false,
        "postfix": false,
        "binop": null
      },
      "value": "state",
      "start": 186,
      "end": 191,
      "loc": {
        "start": {
          "line": 9,
          "column": 19
        },
        "end": {
          "line": 9,
          "column": 24
        }
      }
    },
    {
      "type": {
        "label": ";",
        "beforeExpr": true,
        "startsExpr": false,
        "rightAssociative": false,
        "isLoop": false,
        "isAssign": false,
        "prefix": false,
        "postfix": false,
        "binop": null,
        "updateContext": null
      },
      "start": 191,
      "end": 192,
      "loc": {
        "start": {
          "line": 9,
          "column": 24
        },
        "end": {
          "line": 9,
          "column": 25
        }
      }
    },
    {
      "type": {
        "label": "}",
        "beforeExpr": false,
        "startsExpr": false,
        "rightAssociative": false,
        "isLoop": false,
        "isAssign": false,
        "prefix": false,
        "postfix": false,
        "binop": null
      },
      "start": 197,
      "end": 198,
      "loc": {
        "start": {
          "line": 10,
          "column": 4
        },
        "end": {
          "line": 10,
          "column": 5
        }
      }
    },
    {
      "type": {
        "label": "}",
        "beforeExpr": false,
        "startsExpr": false,
        "rightAssociative": false,
        "isLoop": false,
        "isAssign": false,
        "prefix": false,
        "postfix": false,
        "binop": null
      },
      "start": 199,
      "end": 200,
      "loc": {
        "start": {
          "line": 11,
          "column": 0
        },
        "end": {
          "line": 11,
          "column": 1
        }
      }
    },
    {
      "type": {
        "label": ";",
        "beforeExpr": true,
        "startsExpr": false,
        "rightAssociative": false,
        "isLoop": false,
        "isAssign": false,
        "prefix": false,
        "postfix": false,
        "binop": null,
        "updateContext": null
      },
      "start": 200,
      "end": 201,
      "loc": {
        "start": {
          "line": 11,
          "column": 1
        },
        "end": {
          "line": 11,
          "column": 2
        }
      }
    },
    {
      "type": "CommentBlock",
      "value": " Selectors ",
      "start": 203,
      "end": 218,
      "loc": {
        "start": {
          "line": 13,
          "column": 0
        },
        "end": {
          "line": 13,
          "column": 15
        }
      }
    },
    {
      "type": "CommentLine",
      "value": " Export Reducer",
      "start": 220,
      "end": 237,
      "loc": {
        "start": {
          "line": 15,
          "column": 0
        },
        "end": {
          "line": 15,
          "column": 17
        }
      }
    },
    {
      "type": {
        "label": "export",
        "keyword": "export",
        "beforeExpr": false,
        "startsExpr": false,
        "rightAssociative": false,
        "isLoop": false,
        "isAssign": false,
        "prefix": false,
        "postfix": false,
        "binop": null,
        "updateContext": null
      },
      "value": "export",
      "start": 238,
      "end": 244,
      "loc": {
        "start": {
          "line": 16,
          "column": 0
        },
        "end": {
          "line": 16,
          "column": 6
        }
      }
    },
    {
      "type": {
        "label": "default",
        "keyword": "default",
        "beforeExpr": true,
        "startsExpr": false,
        "rightAssociative": false,
        "isLoop": false,
        "isAssign": false,
        "prefix": false,
        "postfix": false,
        "binop": null,
        "updateContext": null
      },
      "value": "default",
      "start": 245,
      "end": 252,
      "loc": {
        "start": {
          "line": 16,
          "column": 7
        },
        "end": {
          "line": 16,
          "column": 14
        }
      }
    },
    {
      "type": {
        "label": "name",
        "beforeExpr": false,
        "startsExpr": true,
        "rightAssociative": false,
        "isLoop": false,
        "isAssign": false,
        "prefix": false,
        "postfix": false,
        "binop": null
      },
      "value": "ContainerReducer",
      "start": 253,
      "end": 269,
      "loc": {
        "start": {
          "line": 16,
          "column": 15
        },
        "end": {
          "line": 16,
          "column": 31
        }
      }
    },
    {
      "type": {
        "label": ";",
        "beforeExpr": true,
        "startsExpr": false,
        "rightAssociative": false,
        "isLoop": false,
        "isAssign": false,
        "prefix": false,
        "postfix": false,
        "binop": null,
        "updateContext": null
      },
      "start": 269,
      "end": 270,
      "loc": {
        "start": {
          "line": 16,
          "column": 31
        },
        "end": {
          "line": 16,
          "column": 32
        }
      }
    },
    {
      "type": {
        "label": "eof",
        "beforeExpr": false,
        "startsExpr": false,
        "rightAssociative": false,
        "isLoop": false,
        "isAssign": false,
        "prefix": false,
        "postfix": false,
        "binop": null,
        "updateContext": null
      },
      "start": 271,
      "end": 271,
      "loc": {
        "start": {
          "line": 17,
          "column": 0
        },
        "end": {
          "line": 17,
          "column": 0
        }
      }
    }
  ]
}