{
  "type": "File",
  "start": 0,
  "end": 138,
  "loc": {
    "start": {
      "line": 1,
      "column": 0
    },
    "end": {
      "line": 9,
      "column": 0
    }
  },
  "program": {
    "type": "Program",
    "start": 0,
    "end": 138,
    "loc": {
      "start": {
        "line": 1,
        "column": 0
      },
      "end": {
        "line": 9,
        "column": 0
      }
    },
    "sourceType": "module",
    "body": [
      {
        "type": "ExportNamedDeclaration",
        "start": 0,
        "end": 41,
        "loc": {
          "start": {
            "line": 1,
            "column": 0
          },
          "end": {
            "line": 1,
            "column": 41
          }
        },
        "specifiers": [],
        "source": null,
        "declaration": {
          "type": "VariableDeclaration",
          "start": 7,
          "end": 41,
          "loc": {
            "start": {
              "line": 1,
              "column": 7
            },
            "end": {
              "line": 1,
              "column": 41
            }
          },
          "declarations": [
            {
              "type": "VariableDeclarator",
              "start": 13,
              "end": 40,
              "loc": {
                "start": {
                  "line": 1,
                  "column": 13
                },
                "end": {
                  "line": 1,
                  "column": 40
                }
              },
              "id": {
                "type": "Identifier",
                "start": 13,
                "end": 24,
                "loc": {
                  "start": {
                    "line": 1,
                    "column": 13
                  },
                  "end": {
                    "line": 1,
                    "column": 24
                  },
                  "identifierName": "CHANGE_VIEW"
                },
                "name": "CHANGE_VIEW"
              },
              "init": {
                "type": "StringLiteral",
                "start": 27,
                "end": 40,
                "loc": {
                  "start": {
                    "line": 1,
                    "column": 27
                  },
                  "end": {
                    "line": 1,
                    "column": 40
                  }
                },
                "extra": {
                  "rawValue": "CHANGE_VIEW",
                  "raw": "'CHANGE_VIEW'"
                },
                "value": "CHANGE_VIEW"
              }
            }
          ],
          "kind": "const",
          "leadingComments": [],
          "trailingComments": []
        }
      },
      {
        "type": "ExportNamedDeclaration",
        "start": 43,
        "end": 137,
        "loc": {
          "start": {
            "line": 3,
            "column": 0
          },
          "end": {
            "line": 8,
            "column": 1
          }
        },
        "specifiers": [],
        "source": null,
        "declaration": {
          "type": "FunctionDeclaration",
          "start": 50,
          "end": 137,
          "loc": {
            "start": {
              "line": 3,
              "column": 7
            },
            "end": {
              "line": 8,
              "column": 1
            }
          },
          "id": {
            "type": "Identifier",
            "start": 59,
            "end": 69,
            "loc": {
              "start": {
                "line": 3,
                "column": 16
              },
              "end": {
                "line": 3,
                "column": 26
              },
              "identifierName": "changeView"
            },
            "name": "changeView"
          },
          "generator": false,
          "expression": false,
          "async": false,
          "params": [
            {
              "type": "Identifier",
              "start": 70,
              "end": 74,
              "loc": {
                "start": {
                  "line": 3,
                  "column": 27
                },
                "end": {
                  "line": 3,
                  "column": 31
                },
                "identifierName": "view"
              },
              "name": "view"
            }
          ],
          "body": {
            "type": "BlockStatement",
            "start": 75,
            "end": 137,
            "loc": {
              "start": {
                "line": 3,
                "column": 32
              },
              "end": {
                "line": 8,
                "column": 1
              }
            },
            "body": [
              {
                "type": "ReturnStatement",
                "start": 81,
                "end": 135,
                "loc": {
                  "start": {
                    "line": 4,
                    "column": 4
                  },
                  "end": {
                    "line": 7,
                    "column": 5
                  }
                },
                "argument": {
                  "type": "ObjectExpression",
                  "start": 88,
                  "end": 135,
                  "loc": {
                    "start": {
                      "line": 4,
                      "column": 11
                    },
                    "end": {
                      "line": 7,
                      "column": 5
                    }
                  },
                  "properties": [
                    {
                      "type": "ObjectProperty",
                      "start": 98,
                      "end": 115,
                      "loc": {
                        "start": {
                          "line": 5,
                          "column": 8
                        },
                        "end": {
                          "line": 5,
                          "column": 25
                        }
                      },
                      "method": false,
                      "shorthand": false,
                      "computed": false,
                      "key": {
                        "type": "Identifier",
                        "start": 98,
                        "end": 102,
                        "loc": {
                          "start": {
                            "line": 5,
                            "column": 8
                          },
                          "end": {
                            "line": 5,
                            "column": 12
                          },
                          "identifierName": "type"
                        },
                        "name": "type"
                      },
                      "value": {
                        "type": "Identifier",
                        "start": 104,
                        "end": 115,
                        "loc": {
                          "start": {
                            "line": 5,
                            "column": 14
                          },
                          "end": {
                            "line": 5,
                            "column": 25
                          },
                          "identifierName": "CHANGE_VIEW"
                        },
                        "name": "CHANGE_VIEW"
                      }
                    },
                    {
                      "type": "ObjectProperty",
                      "start": 125,
                      "end": 129,
                      "loc": {
                        "start": {
                          "line": 6,
                          "column": 8
                        },
                        "end": {
                          "line": 6,
                          "column": 12
                        }
                      },
                      "method": false,
                      "shorthand": true,
                      "computed": false,
                      "key": {
                        "type": "Identifier",
                        "start": 125,
                        "end": 129,
                        "loc": {
                          "start": {
                            "line": 6,
                            "column": 8
                          },
                          "end": {
                            "line": 6,
                            "column": 12
                          },
                          "identifierName": "view"
                        },
                        "name": "view"
                      },
                      "value": {
                        "type": "Identifier",
                        "start": 125,
                        "end": 129,
                        "loc": {
                          "start": {
                            "line": 6,
                            "column": 8
                          },
                          "end": {
                            "line": 6,
                            "column": 12
                          },
                          "identifierName": "view"
                        },
                        "name": "view"
                      },
                      "extra": {
                        "shorthand": true
                      }
                    }
                  ]
                }
              }
            ],
            "directives": []
          },
          "leadingComments": [],
          "trailingComments": []
        }
      }
    ],
    "directives": []
  },
  "comments": [],
  "tokens": [
    {
      "type": {
        "label": "export",
        "keyword": "export",
        "beforeExpr": false,
        "startsExpr": false,
        "rightAssociative": false,
        "isLoop": false,
        "isAssign": false,
        "prefix": false,
        "postfix": false,
        "binop": null,
        "updateContext": null
      },
      "value": "export",
      "start": 0,
      "end": 6,
      "loc": {
        "start": {
          "line": 1,
          "column": 0
        },
        "end": {
          "line": 1,
          "column": 6
        }
      }
    },
    {
      "type": {
        "label": "const",
        "keyword": "const",
        "beforeExpr": false,
        "startsExpr": false,
        "rightAssociative": false,
        "isLoop": false,
        "isAssign": false,
        "prefix": false,
        "postfix": false,
        "binop": null,
        "updateContext": null
      },
      "value": "const",
      "start": 7,
      "end": 12,
      "loc": {
        "start": {
          "line": 1,
          "column": 7
        },
        "end": {
          "line": 1,
          "column": 12
        }
      }
    },
    {
      "type": {
        "label": "name",
        "beforeExpr": false,
        "startsExpr": true,
        "rightAssociative": false,
        "isLoop": false,
        "isAssign": false,
        "prefix": false,
        "postfix": false,
        "binop": null
      },
      "value": "CHANGE_VIEW",
      "start": 13,
      "end": 24,
      "loc": {
        "start": {
          "line": 1,
          "column": 13
        },
        "end": {
          "line": 1,
          "column": 24
        }
      }
    },
    {
      "type": {
        "label": "=",
        "beforeExpr": true,
        "startsExpr": false,
        "rightAssociative": false,
        "isLoop": false,
        "isAssign": true,
        "prefix": false,
        "postfix": false,
        "binop": null,
        "updateContext": null
      },
      "value": "=",
      "start": 25,
      "end": 26,
      "loc": {
        "start": {
          "line": 1,
          "column": 25
        },
        "end": {
          "line": 1,
          "column": 26
        }
      }
    },
    {
      "type": {
        "label": "string",
        "beforeExpr": false,
        "startsExpr": true,
        "rightAssociative": false,
        "isLoop": false,
        "isAssign": false,
        "prefix": false,
        "postfix": false,
        "binop": null,
        "updateContext": null
      },
      "value": "CHANGE_VIEW",
      "start": 27,
      "end": 40,
      "loc": {
        "start": {
          "line": 1,
          "column": 27
        },
        "end": {
          "line": 1,
          "column": 40
        }
      }
    },
    {
      "type": {
        "label": ";",
        "beforeExpr": true,
        "startsExpr": false,
        "rightAssociative": false,
        "isLoop": false,
        "isAssign": false,
        "prefix": false,
        "postfix": false,
        "binop": null,
        "updateContext": null
      },
      "start": 40,
      "end": 41,
      "loc": {
        "start": {
          "line": 1,
          "column": 40
        },
        "end": {
          "line": 1,
          "column": 41
        }
      }
    },
    {
      "type": {
        "label": "export",
        "keyword": "export",
        "beforeExpr": false,
        "startsExpr": false,
        "rightAssociative": false,
        "isLoop": false,
        "isAssign": false,
        "prefix": false,
        "postfix": false,
        "binop": null,
        "updateContext": null
      },
      "value": "export",
      "start": 43,
      "end": 49,
      "loc": {
        "start": {
          "line": 3,
          "column": 0
        },
        "end": {
          "line": 3,
          "column": 6
        }
      }
    },
    {
      "type": {
        "label": "function",
        "keyword": "function",
        "beforeExpr": false,
        "startsExpr": true,
        "rightAssociative": false,
        "isLoop": false,
        "isAssign": false,
        "prefix": false,
        "postfix": false,
        "binop": null
      },
      "value": "function",
      "start": 50,
      "end": 58,
      "loc": {
        "start": {
          "line": 3,
          "column": 7
        },
        "end": {
          "line": 3,
          "column": 15
        }
      }
    },
    {
      "type": {
        "label": "name",
        "beforeExpr": false,
        "startsExpr": true,
        "rightAssociative": false,
        "isLoop": false,
        "isAssign": false,
        "prefix": false,
        "postfix": false,
        "binop": null
      },
      "value": "changeView",
      "start": 59,
      "end": 69,
      "loc": {
        "start": {
          "line": 3,
          "column": 16
        },
        "end": {
          "line": 3,
          "column": 26
        }
      }
    },
    {
      "type": {
        "label": "(",
        "beforeExpr": true,
        "startsExpr": true,
        "rightAssociative": false,
        "isLoop": false,
        "isAssign": false,
        "prefix": false,
        "postfix": false,
        "binop": null
      },
      "start": 69,
      "end": 70,
      "loc": {
        "start": {
          "line": 3,
          "column": 26
        },
        "end": {
          "line": 3,
          "column": 27
        }
      }
    },
    {
      "type": {
        "label": "name",
        "beforeExpr": false,
        "startsExpr": true,
        "rightAssociative": false,
        "isLoop": false,
        "isAssign": false,
        "prefix": false,
        "postfix": false,
        "binop": null
      },
      "value": "view",
      "start": 70,
      "end": 74,
      "loc": {
        "start": {
          "line": 3,
          "column": 27
        },
        "end": {
          "line": 3,
          "column": 31
        }
      }
    },
    {
      "type": {
        "label": ")",
        "beforeExpr": false,
        "startsExpr": false,
        "rightAssociative": false,
        "isLoop": false,
        "isAssign": false,
        "prefix": false,
        "postfix": false,
        "binop": null
      },
      "start": 74,
      "end": 75,
      "loc": {
        "start": {
          "line": 3,
          "column": 31
        },
        "end": {
          "line": 3,
          "column": 32
        }
      }
    },
    {
      "type": {
        "label": "{",
        "beforeExpr": true,
        "startsExpr": true,
        "rightAssociative": false,
        "isLoop": false,
        "isAssign": false,
        "prefix": false,
        "postfix": false,
        "binop": null
      },
      "start": 75,
      "end": 76,
      "loc": {
        "start": {
          "line": 3,
          "column": 32
        },
        "end": {
          "line": 3,
          "column": 33
        }
      }
    },
    {
      "type": {
        "label": "return",
        "keyword": "return",
        "beforeExpr": true,
        "startsExpr": false,
        "rightAssociative": false,
        "isLoop": false,
        "isAssign": false,
        "prefix": false,
        "postfix": false,
        "binop": null,
        "updateContext": null
      },
      "value": "return",
      "start": 81,
      "end": 87,
      "loc": {
        "start": {
          "line": 4,
          "column": 4
        },
        "end": {
          "line": 4,
          "column": 10
        }
      }
    },
    {
      "type": {
        "label": "{",
        "beforeExpr": true,
        "startsExpr": true,
        "rightAssociative": false,
        "isLoop": false,
        "isAssign": false,
        "prefix": false,
        "postfix": false,
        "binop": null
      },
      "start": 88,
      "end": 89,
      "loc": {
        "start": {
          "line": 4,
          "column": 11
        },
        "end": {
          "line": 4,
          "column": 12
        }
      }
    },
    {
      "type": {
        "label": "name",
        "beforeExpr": false,
        "startsExpr": true,
        "rightAssociative": false,
        "isLoop": false,
        "isAssign": false,
        "prefix": false,
        "postfix": false,
        "binop": null
      },
      "value": "type",
      "start": 98,
      "end": 102,
      "loc": {
        "start": {
          "line": 5,
          "column": 8
        },
        "end": {
          "line": 5,
          "column": 12
        }
      }
    },
    {
      "type": {
        "label": ":",
        "beforeExpr": true,
        "startsExpr": false,
        "rightAssociative": false,
        "isLoop": false,
        "isAssign": false,
        "prefix": false,
        "postfix": false,
        "binop": null,
        "updateContext": null
      },
      "start": 102,
      "end": 103,
      "loc": {
        "start": {
          "line": 5,
          "column": 12
        },
        "end": {
          "line": 5,
          "column": 13
        }
      }
    },
    {
      "type": {
        "label": "name",
        "beforeExpr": false,
        "startsExpr": true,
        "rightAssociative": false,
        "isLoop": false,
        "isAssign": false,
        "prefix": false,
        "postfix": false,
        "binop": null
      },
      "value": "CHANGE_VIEW",
      "start": 104,
      "end": 115,
      "loc": {
        "start": {
          "line": 5,
          "column": 14
        },
        "end": {
          "line": 5,
          "column": 25
        }
      }
    },
    {
      "type": {
        "label": ",",
        "beforeExpr": true,
        "startsExpr": false,
        "rightAssociative": false,
        "isLoop": false,
        "isAssign": false,
        "prefix": false,
        "postfix": false,
        "binop": null,
        "updateContext": null
      },
      "start": 115,
      "end": 116,
      "loc": {
        "start": {
          "line": 5,
          "column": 25
        },
        "end": {
          "line": 5,
          "column": 26
        }
      }
    },
    {
      "type": {
        "label": "name",
        "beforeExpr": false,
        "startsExpr": true,
        "rightAssociative": false,
        "isLoop": false,
        "isAssign": false,
        "prefix": false,
        "postfix": false,
        "binop": null
      },
      "value": "view",
      "start": 125,
      "end": 129,
      "loc": {
        "start": {
          "line": 6,
          "column": 8
        },
        "end": {
          "line": 6,
          "column": 12
        }
      }
    },
    {
      "type": {
        "label": "}",
        "beforeExpr": false,
        "startsExpr": false,
        "rightAssociative": false,
        "isLoop": false,
        "isAssign": false,
        "prefix": false,
        "postfix": false,
        "binop": null
      },
      "start": 134,
      "end": 135,
      "loc": {
        "start": {
          "line": 7,
          "column": 4
        },
        "end": {
          "line": 7,
          "column": 5
        }
      }
    },
    {
      "type": {
        "label": "}",
        "beforeExpr": false,
        "startsExpr": false,
        "rightAssociative": false,
        "isLoop": false,
        "isAssign": false,
        "prefix": false,
        "postfix": false,
        "binop": null
      },
      "start": 136,
      "end": 137,
      "loc": {
        "start": {
          "line": 8,
          "column": 0
        },
        "end": {
          "line": 8,
          "column": 1
        }
      }
    },
    {
      "type": {
        "label": "eof",
        "beforeExpr": false,
        "startsExpr": false,
        "rightAssociative": false,
        "isLoop": false,
        "isAssign": false,
        "prefix": false,
        "postfix": false,
        "binop": null,
        "updateContext": null
      },
      "start": 138,
      "end": 138,
      "loc": {
        "start": {
          "line": 9,
          "column": 0
        },
        "end": {
          "line": 9,
          "column": 0
        }
      }
    }
  ]
}